Elasticsearch54ZhongwenWendang/README.md
Elasticsearch54ZhongwenWendang/__init__.py
Elasticsearch54ZhongwenWendang/__main__.py
Elasticsearch54ZhongwenWendang/file.epub
Elasticsearch54ZhongwenWendang/index.html
Elasticsearch54ZhongwenWendang/css/__init__.py
Elasticsearch54ZhongwenWendang/css/annotations.css
Elasticsearch54ZhongwenWendang/css/main.css
Elasticsearch54ZhongwenWendang/css/normalize.css
Elasticsearch54ZhongwenWendang/css/popup.css
Elasticsearch54ZhongwenWendang/font/__init__.py
Elasticsearch54ZhongwenWendang/font/fontello.eot
Elasticsearch54ZhongwenWendang/font/fontello.svg
Elasticsearch54ZhongwenWendang/font/fontello.ttf
Elasticsearch54ZhongwenWendang/font/fontello.woff
Elasticsearch54ZhongwenWendang/img/__init__.py
Elasticsearch54ZhongwenWendang/img/annotator-glyph-sprite.png
Elasticsearch54ZhongwenWendang/img/annotator-icon-sprite.png
Elasticsearch54ZhongwenWendang/img/apple-touch-icon.png
Elasticsearch54ZhongwenWendang/img/cancelfullscreen.png
Elasticsearch54ZhongwenWendang/img/close.png
Elasticsearch54ZhongwenWendang/img/fullscreen.png
Elasticsearch54ZhongwenWendang/img/loader.gif
Elasticsearch54ZhongwenWendang/img/menu-icon.png
Elasticsearch54ZhongwenWendang/img/save.png
Elasticsearch54ZhongwenWendang/img/saved.png
Elasticsearch54ZhongwenWendang/img/settings-s.png
Elasticsearch54ZhongwenWendang/img/settings.png
Elasticsearch54ZhongwenWendang/img/star.png
Elasticsearch54ZhongwenWendang/js/__init__.py
Elasticsearch54ZhongwenWendang/js/epub.js
Elasticsearch54ZhongwenWendang/js/epub.min.js
Elasticsearch54ZhongwenWendang/js/epub.min.map
Elasticsearch54ZhongwenWendang/js/hooks.min.js
Elasticsearch54ZhongwenWendang/js/hooks.min.map
Elasticsearch54ZhongwenWendang/js/reader.js
Elasticsearch54ZhongwenWendang/js/reader.js.map
Elasticsearch54ZhongwenWendang/js/reader.min.js
Elasticsearch54ZhongwenWendang/js/reader.min.map
Elasticsearch54ZhongwenWendang/js/hooks/__init__.py
Elasticsearch54ZhongwenWendang/js/hooks/extensions/__init__.py
elasticsearch_5_4_zhongwen_wendang-2024.3.2.0.dist-info/METADATA
elasticsearch_5_4_zhongwen_wendang-2024.3.2.0.dist-info/WHEEL
elasticsearch_5_4_zhongwen_wendang-2024.3.2.0.dist-info/entry_points.txt
elasticsearch_5_4_zhongwen_wendang-2024.3.2.0.dist-info/top_level.txt
elasticsearch_5_4_zhongwen_wendang-2024.3.2.0.dist-info/RECORD
